youtubi/__init__.py
youtubi-1.2.3.dist-info/METADATA
youtubi-1.2.3.dist-info/WHEEL
youtubi-1.2.3.dist-info/top_level.txt
youtubi-1.2.3.dist-info/RECORD
