Metadata-Version: 2.1
Name: youtubi
Version: 1.2.3
Summary: Download youtube videos 
Home-page: https://gitlab.com/isampypi/youtubi
Author: Mhadhbi Issam
Author-email: mhadhbixissam@gmail.com
Classifier: Programming Language :: Python :: 3
Classifier: License :: OSI Approved :: MIT License
Classifier: Operating System :: OS Independent
Requires-Dist: pytube
Requires-Dist: lxml
Requires-Dist: beautifulsoup4
Requires-Dist: tqdm
Requires-Dist: moviepy
Requires-Dist: ffmpeg
